pyczinv/__init__.py
pyczinv/coupled_inversion.py
pyczinv/inversion_utils.py
pyczinv/joint_inversion.py
pyczinv/petrophysics_utils.py
pyczinv/solver.py
pyczinv/time_lapse_inversion.py
pyczinv/data/__init__.py
pyczinv/data/dataloader.py
PyCZINV-0.1.4.dist-info/METADATA
PyCZINV-0.1.4.dist-info/WHEEL
PyCZINV-0.1.4.dist-info/top_level.txt
PyCZINV-0.1.4.dist-info/RECORD
